sstpy/__init__.py
sstpy/sstable.py
sstpy/sstable_builder.py
sstpy/sstable_partition.py
sstpy/lib/libsstable_internal.so
sstpy-0.1.6.dist-info/METADATA
sstpy-0.1.6.dist-info/WHEEL
sstpy-0.1.6.dist-info/top_level.txt
sstpy-0.1.6.dist-info/RECORD
