Metadata-Version: 2.1
Name: sstpy
Version: 0.1.6
Summary: A python wrapper project for sstable
Home-page: https://codeup.aliyun.com/64ddb0a87f62ff9b3d23ca15/py_sstable
Author: HankyZhao
Author-email: zhq980115@gmail.com
Classifier: Programming Language :: Python :: 3
Classifier: License :: OSI Approved :: MIT License
Classifier: Operating System :: OS Independent
Requires-Python: >=3.6
